buildstream_plugins_community/__init__.py
buildstream_plugins_community/elements/__init__.py
buildstream_plugins_community/elements/bazel_build.py
buildstream_plugins_community/elements/bazel_build.yaml
buildstream_plugins_community/elements/bazelize.py
buildstream_plugins_community/elements/bazelize.yaml
buildstream_plugins_community/elements/check_forbidden.py
buildstream_plugins_community/elements/collect_integration.py
buildstream_plugins_community/elements/collect_manifest.py
buildstream_plugins_community/elements/dpkg_build.py
buildstream_plugins_community/elements/dpkg_build.yaml
buildstream_plugins_community/elements/dpkg_deploy.py
buildstream_plugins_community/elements/dpkg_deploy.yaml
buildstream_plugins_community/elements/fastboot_bootimg.py
buildstream_plugins_community/elements/fastboot_bootimg.yaml
buildstream_plugins_community/elements/fastboot_ext4.py
buildstream_plugins_community/elements/fastboot_ext4.yaml
buildstream_plugins_community/elements/flatpak_image.py
buildstream_plugins_community/elements/flatpak_image.yaml
buildstream_plugins_community/elements/flatpak_repo.py
buildstream_plugins_community/elements/flatpak_repo.yaml
buildstream_plugins_community/elements/makemaker.py
buildstream_plugins_community/elements/makemaker.yaml
buildstream_plugins_community/elements/modulebuild.py
buildstream_plugins_community/elements/modulebuild.yaml
buildstream_plugins_community/elements/oci.py
buildstream_plugins_community/elements/ostree.py
buildstream_plugins_community/elements/ostree.yaml
buildstream_plugins_community/elements/pyproject.py
buildstream_plugins_community/elements/pyproject.yaml
buildstream_plugins_community/elements/qmake.py
buildstream_plugins_community/elements/qmake.yaml
buildstream_plugins_community/elements/snap_image.py
buildstream_plugins_community/elements/snap_image.yaml
buildstream_plugins_community/elements/tar_element.py
buildstream_plugins_community/elements/tar_element.yaml
buildstream_plugins_community/elements/x86image.py
buildstream_plugins_community-2.1.1.dist-info/licenses/LICENSE
buildstream_plugins_community-2.1.1.dist-info/METADATA
buildstream_plugins_community-2.1.1.dist-info/WHEEL
buildstream_plugins_community-2.1.1.dist-info/entry_points.txt
buildstream_plugins_community-2.1.1.dist-info/top_level.txt
buildstream_plugins_community-2.1.1.dist-info/RECORD
