Metadata-Version: 2.4
Name: buildstream-plugins-community
Version: 2.1.1
Summary: A collection of community-maintained plugins.
License: LGPL-2.1-or-later
Project-URL: Homepage, https://buildstream.gitlab.io/buildstream-plugins-community/
Project-URL: Documentation, https://buildstream.gitlab.io/buildstream-plugins-community/
Project-URL: Repository, https://gitlab.com/BuildStream/buildstream-plugins-community
Classifier: Programming Language :: Python :: 3
Requires-Python: >=3.9
License-File: LICENSE
Requires-Dist: packaging
Provides-Extra: bazel
Requires-Dist: requests; extra == "bazel"
Provides-Extra: deb
Requires-Dist: arpy; extra == "deb"
Dynamic: license-file
